[
  {
    "title": "Six Things McKinsey Learned from a Year of Agentic AI (That Matter for FP&A)",
    "slug": "mckinsey-agentic-ai-fpa",
    "date": "2026-02-26",
    "excerpt": "McKinsey analyzed 50+ agentic AI builds and distilled six lessons. Here's the FP&A-specific read on each one.",
    "tags": [
      "AI in Finance",
      "Strategy"
    ]
  }
  {
  "title": "Reasonable vs Defensible vs Probability-Weighted Forecasts",
  "slug": "probability-weighted-forecasting",
  "date": "2026-03-06",
  "excerpt": "A forecast that looks reasonable is only the starting point. Strong FP&A teams push further by making assumptions defensible and ultimately building probability-weighted scenarios that show leadership the real range of outcomes.",
  "tags": ["FP&A", "Forecasting", "Financial Modeling", "Decision Making", "AI in Finance"]
}
]
